setup.py
mcat/__init__.py
mcat.egg-info/PKG-INFO
mcat.egg-info/SOURCES.txt
mcat.egg-info/dependency_links.txt
mcat.egg-info/entry_points.txt
mcat.egg-info/not-zip-safe
mcat.egg-info/requires.txt
mcat.egg-info/top_level.txt