Metadata-Version: 1.0
Name: mcat
Version: 1.0
Summary: Run multiple commands and capture their output to 1 stream
Home-page: http://github.com/ryazwinski/mcat
Author: Rick Yazwinski
Author-email: rick@thinker.ca
License: MIT
Platform: UNKNOWN
